pkgdb/__init__.py
pkgdb/__main__.py
pkgdb/api.py
pkgdb/badges.py
pkgdb/cli.py
pkgdb/db.py
pkgdb/export.py
pkgdb/logging.py
pkgdb/reports.py
pkgdb/service.py
pkgdb/types.py
pkgdb/utils.py
pkgdb-0.1.7.dist-info/licenses/LICENSE
pkgdb-0.1.7.dist-info/WHEEL
pkgdb-0.1.7.dist-info/entry_points.txt
pkgdb-0.1.7.dist-info/METADATA
pkgdb-0.1.7.dist-info/RECORD
