Metadata-Version: 2.4
Name: pkgdb
Version: 0.1.7
Summary: Track, store and query your PyPI package download statistics
Keywords: pypi,statistics,downloads,analytics,cli
Author: Shakeeb Alireza
Author-email: Shakeeb Alireza <shakfu@users.noreply.github.com>
License-Expression: MIT
License-File: LICENSE
Classifier: Development Status :: 4 - Beta
Classifier: Environment :: Console
Classifier: Intended Audience :: Developers
Classifier: License :: OSI Approved :: BSD License
Classifier: Operating System :: OS Independent
Classifier: Programming Language :: Python :: 3
Classifier: Programming Language :: Python :: 3.10
Classifier: Programming Language :: Python :: 3.11
Classifier: Programming Language :: Python :: 3.12
Classifier: Programming Language :: Python :: 3.13
Classifier: Programming Language :: Python :: 3.14
Classifier: Topic :: Software Development :: Libraries :: Python Modules
Classifier: Topic :: System :: Software Distribution
Requires-Dist: pypistats>=1.12.0
Requires-Dist: tabulate>=0.9.0
Requires-Python: >=3.10
Project-URL: Homepage, https://github.com/shakfu/pkgdb
Project-URL: Repository, https://github.com/shakfu/pkgdb
Project-URL: Issues, https://github.com/shakfu/pkgdb/issues
